smthrandom/__init__.py
smthrandom/core.py
smthrandom-0.2.0.dist-info/METADATA
smthrandom-0.2.0.dist-info/WHEEL
smthrandom-0.2.0.dist-info/top_level.txt
smthrandom-0.2.0.dist-info/RECORD
