Metadata-Version: 2.4
Name: smthrandom
Version: 0.2.0
Summary: A random useless library
Author-email: Jason N <jason.vbnguyen@gmail.com>
License: MIT
Requires-Dist: random
